puzzle_slider_captcha/__init__.py
puzzle_slider_captcha/_solver.py
puzzle_slider_captcha/_transforms.py
puzzle_slider_captcha-0.1.0.dist-info/METADATA
puzzle_slider_captcha-0.1.0.dist-info/WHEEL
puzzle_slider_captcha-0.1.0.dist-info/top_level.txt
puzzle_slider_captcha-0.1.0.dist-info/RECORD
