Metadata-Version: 2.4
Name: puzzle_slider_captcha
Version: 0.1.0
Summary: A robust OpenCV-based solver for slider captchas (Puzzle matching)
Author-email: Your Name <your.email@example.com>
License: MIT
Keywords: captcha,slider,geetest,opencv,solver
Classifier: Development Status :: 4 - Beta
Classifier: Intended Audience :: Developers
Classifier: License :: OSI Approved :: MIT License
Classifier: Programming Language :: Python :: 3
Requires-Python: >=3.8
Requires-Dist: opencv-python>=4.0.0
Requires-Dist: numpy>=1.19.0
